.setup.py
tbapi/__init__.py
tbapi/main.py
tbapi.egg-info/PKG-INFO
tbapi.egg-info/SOURCES.txt
tbapi.egg-info/dependency_links.txt
tbapi.egg-info/not-zip-safe
tbapi.egg-info/requires.txt
tbapi.egg-info/top_level.txt