Metadata-Version: 1.0
Name: tbapi
Version: 1.0.1
Summary: A Python Library for connection to The Blue Alliance API v2 | Created by Plasma Robotics, Team 2403
Home-page: https://github.com/PlasmaRobotics2403/TBA-PythonAPI
Author: Plasma Robotics | FRC Team 2403
Author-email: plasma2403@gmail.com
License: MIT
Platform: UNKNOWN
